LICENSE
MANIFEST.in
README.md
setup.py
dock/__init__.py
dock/dock.py
dock.egg-info/PKG-INFO
dock.egg-info/SOURCES.txt
dock.egg-info/dependency_links.txt
dock.egg-info/requires.txt
dock.egg-info/top_level.txt