Metadata-Version: 1.1
Name: dock
Version: 0.0.1
Summary: Batch job queue for ML inference.
Home-page: https://github.com/vzhong/dock
Author: Victor Zhong
Author-email: victor@victorzhong.com
License: MIT
Keywords: text nlp machine-learning
Platform: UNKNOWN
Classifier: Development Status :: 3 - Alpha
Classifier: Intended Audience :: Developers
Classifier: License :: OSI Approved :: MIT License
Classifier: Programming Language :: Python :: 3.5
